{
    "id": "4d12c985b7fdb2d0bf662f41260d0003d0acf10f",
    "meta": {
        "filename": "dod-2014_PROCUREMENT_2014_AIRFORCE_OTHER_PROCUREMENT_MasterJustificationBook_Air_Force_PB_2014.zzz_unzipped_PROCUREMENT_MasterJustificationBook_Air_Force_PB_2014.xml",
        "budget_year": "2014",
        "budget_cycle": "PB",
        "submission_date": "2013-04",
        "service_agency_name": "Air Force",
        "appropriation_code": "3080F",
        "appropriation_name": "Other Procurement, Air Force"
    },
    "record": {
        "@quantityUnits": "Each",
        "@quantityUnitName": "Each",
        "@unitCostUnits": "Millions",
        "@totalCostUnits": "Millions",
        "LineItemNumber": {
            "val": "861900"
        },
        "LineItemTitle": {
            "val": "Spares and Repair Parts"
        },
        "P1LineNumber": {
            "val": "69"
        },
        "BudgetYear": {
            "val": "2014"
        },
        "BudgetCycle": {
            "val": "PB"
        },
        "SubmissionDate": {
            "val": "2013-04"
        },
        "ServiceAgencyName": {
            "val": "Air Force"
        },
        "AppropriationNumber": {
            "val": "3080F"
        },
        "AppropriationTitle": {
            "val": "Other Procurement, Air Force"
        },
        "BudgetActivityNumber": {
            "val": "5"
        },
        "BudgetActivityTitle": {
            "val": "Spares and Repair Parts"
        },
        "BudgetSubActivityNumber": {
            "val": "1"
        },
        "BudgetSubActivityTitle": {
            "val": "Spares And Repair Parts"
        },
        "ResourceSummary": {
            "GrossWeaponSystemCost": {
                "PriorYear": {
                    "val": "22.115"
                },
                "CurrentYear": {
                    "val": "16.963"
                },
                "BudgetYearOneBase": {
                    "val": "25.746"
                },
                "BudgetYearOne": {
                    "val": "25.746"
                },
                "BudgetYearTwo": {
                    "val": "37.195"
                },
                "BudgetYearThree": {
                    "val": "62.194"
                },
                "BudgetYearFour": {
                    "val": "63.88"
                },
                "BudgetYearFive": {
                    "val": "63.826"
                },
                "Continuing": {
                    "val": "true"
                }
            },
            "NetProcurementP1": {
                "PriorYear": {
                    "val": "22.115"
                },
                "CurrentYear": {
                    "val": "16.963"
                },
                "BudgetYearOneBase": {
                    "val": "25.746"
                },
                "BudgetYearOne": {
                    "val": "25.746"
                },
                "BudgetYearTwo": {
                    "val": "37.195"
                },
                "BudgetYearThree": {
                    "val": "62.194"
                },
                "BudgetYearFour": {
                    "val": "63.88"
                },
                "BudgetYearFive": {
                    "val": "63.826"
                },
                "Continuing": {
                    "val": "true"
                }
            },
            "TotalObligationAuthority": {
                "PriorYear": {
                    "val": "22.115"
                },
                "CurrentYear": {
                    "val": "16.963"
                },
                "BudgetYearOneBase": {
                    "val": "25.746"
                },
                "BudgetYearOne": {
                    "val": "25.746"
                },
                "BudgetYearTwo": {
                    "val": "37.195"
                },
                "BudgetYearThree": {
                    "val": "62.194"
                },
                "BudgetYearFour": {
                    "val": "63.88"
                },
                "BudgetYearFive": {
                    "val": "63.826"
                },
                "Continuing": {
                    "val": "true"
                }
            }
        },
        "CostType": {
            "val": "AB"
        },
        "Code": {
            "val": "A"
        },
        "Description": {
            "val": "FY 2013 funding totals include $2.3M requested for Expeditionary Airfield Basing Assets Overseas Contingency Operations.\n\nInitial Spares consist of reparable components, assemblies, subassemblies, and consumable items required as initial stock (including readiness spares package requirements) in support of newly fielded vehicles, communications electronics and telecommunications equipment, and other base maintenance and support equipment items.  Requirements are determined by applying established factors against the acquisition cost of the end items.  The factors are based on historical data of similar equipment, employment\/deployment concepts, production schedules, and other related information."
        },
        "Justification": {
            "val": "Items requested in FY14 are representative of items to be procured.  Items procured during execution may change based on critical equipment needed to\nsupport current Air Force mission requirements."
        },
        "MDAPCode": {
            "val": "537, 166"
        },
        "ItemExhibitList": {
            "P18Item": {
                "Name": {
                    "val": "Spares and Repair Parts"
                },
                "InitialSpares": {
                    "EndItemBudgetActivity": [
                        {
                            "BudgetActivityNumber": {
                                "val": "5"
                            },
                            "BudgetActivityTitle": {
                                "val": "Spares and Repair Parts"
                            },
                            "EndItemList": {
                                "EndItem": [
                                    {
                                        "Name": {
                                            "val": "Air Traffic Control & Landing"
                                        },
                                        "LineItemNumber": {
                                            "val": "833010"
                                        },
                                        "Cost": {
                                            "PriorYear": {
                                                "val": "1.468"
                                            },
                                            "CurrentYear": {
                                                "val": "2.392"
                                            },
                                            "BudgetYearOneBase": {
                                                "val": "3.282"
                                            },
                                            "BudgetYearOneOCO": {
                                                "val": "0.000"
                                            },
                                            "BudgetYearOne": {
                                                "val": "3.282"
                                            },
                                            "BudgetYearTwo": {
                                                "val": "6.041"
                                            },
                                            "BudgetYearThree": {
                                                "val": "5.787"
                                            },
                                            "BudgetYearFour": {
                                                "val": "6.51"
                                            },
                                            "BudgetYearFive": {
                                                "val": "5.406"
                                            },
                                            "Total": {
                                                "val": "30.886"
                                            }
                                        }
                                    },
                                    {
                                        "Name": {
                                            "val": "C-17 AIRCRAFT (IF)"
                                        },
                                        "LineItemNumber": {
                                            "val": "C17A1"
                                        },
                                        "Cost": {
                                            "PriorYear": {
                                                "val": "0.000"
                                            },
                                            "CurrentYear": {
                                                "val": "0.000"
                                            },
                                            "BudgetYearOneBase": {
                                                "val": "0.000"
                                            },
                                            "BudgetYearOneOCO": {
                                                "val": "0.000"
                                            },
                                            "BudgetYearOne": {
                                                "val": "0.000"
                                            },
                                            "BudgetYearTwo": {
                                                "val": "1.1"
                                            },
                                            "BudgetYearThree": {
                                                "val": "1.1"
                                            },
                                            "BudgetYearFour": {
                                                "val": "0.000"
                                            },
                                            "BudgetYearFive": {
                                                "val": "0.000"
                                            },
                                            "Total": {
                                                "val": "2.2"
                                            }
                                        }
                                    },
                                    {
                                        "Name": {
                                            "val": "CHEYENNE MOUNTAIN COMPLEX SPACE TRACK"
                                        },
                                        "LineItemNumber": {
                                            "val": "833160"
                                        },
                                        "Cost": {
                                            "PriorYear": {
                                                "val": "0.000"
                                            },
                                            "CurrentYear": {
                                                "val": "0.772"
                                            },
                                            "BudgetYearOneBase": {
                                                "val": "0.596"
                                            },
                                            "BudgetYearOneOCO": {
                                                "val": "0.000"
                                            },
                                            "BudgetYearOne": {
                                                "val": "0.596"
                                            },
                                            "BudgetYearTwo": {
                                                "val": "0.907"
                                            },
                                            "BudgetYearThree": {
                                                "val": "0.884"
                                            },
                                            "BudgetYearFour": {
                                                "val": "0.824"
                                            },
                                            "BudgetYearFive": {
                                                "val": "0.839"
                                            },
                                            "Total": {
                                                "val": "4.822"
                                            }
                                        }
                                    },
                                    {
                                        "Name": {
                                            "val": "COMBAT TRAINING RANGES,  PE 0207249F"
                                        },
                                        "LineItemNumber": {
                                            "val": "834190"
                                        },
                                        "Cost": {
                                            "PriorYear": {
                                                "val": "0.903"
                                            },
                                            "CurrentYear": {
                                                "val": "0.934"
                                            },
                                            "BudgetYearOneBase": {
                                                "val": "3.698"
                                            },
                                            "BudgetYearOneOCO": {
                                                "val": "0.000"
                                            },
                                            "BudgetYearOne": {
                                                "val": "3.698"
                                            },
                                            "BudgetYearTwo": {
                                                "val": "1.339"
                                            },
                                            "BudgetYearThree": {
                                                "val": "1.119"
                                            },
                                            "BudgetYearFour": {
                                                "val": "0.665"
                                            },
                                            "BudgetYearFive": {
                                                "val": "0.677"
                                            },
                                            "Total": {
                                                "val": "9.335"
                                            }
                                        }
                                    },
                                    {
                                        "Name": {
                                            "val": "Expeditionary Airfield Basing Assets"
                                        },
                                        "LineItemNumber": {
                                            "val": "845420"
                                        },
                                        "Cost": {
                                            "PriorYear": {
                                                "val": "1.426"
                                            },
                                            "CurrentYear": {
                                                "val": "5.191"
                                            },
                                            "BudgetYearOneBase": {
                                                "val": "1.371"
                                            },
                                            "BudgetYearOneOCO": {
                                                "val": "0.000"
                                            },
                                            "BudgetYearOne": {
                                                "val": "1.371"
                                            },
                                            "BudgetYearTwo": {
                                                "val": "2.173"
                                            },
                                            "BudgetYearThree": {
                                                "val": "2.422"
                                            },
                                            "BudgetYearFour": {
                                                "val": "2.141"
                                            },
                                            "BudgetYearFive": {
                                                "val": "2.197"
                                            },
                                            "Total": {
                                                "val": "16.921"
                                            }
                                        }
                                    },
                                    {
                                        "Name": {
                                            "val": "Information Systems Security Program"
                                        },
                                        "LineItemNumber": {
                                            "val": "835070"
                                        },
                                        "Cost": {
                                            "PriorYear": {
                                                "val": "9.771"
                                            },
                                            "CurrentYear": {
                                                "val": "1.666"
                                            },
                                            "BudgetYearOneBase": {
                                                "val": "11.416"
                                            },
                                            "BudgetYearOneOCO": {
                                                "val": "0.000"
                                            },
                                            "BudgetYearOne": {
                                                "val": "11.416"
                                            },
                                            "BudgetYearTwo": {
                                                "val": "6.792"
                                            },
                                            "BudgetYearThree": {
                                                "val": "1.697"
                                            },
                                            "BudgetYearFour": {
                                                "val": "1.726"
                                            },
                                            "BudgetYearFive": {
                                                "val": "1.756"
                                            },
                                            "Total": {
                                                "val": "34.824"
                                            }
                                        }
                                    },
                                    {
                                        "Name": {
                                            "val": "MILSATCOM Terminals"
                                        },
                                        "LineItemNumber": {
                                            "val": "836780"
                                        },
                                        "Cost": {
                                            "PriorYear": {
                                                "val": "0.000"
                                            },
                                            "CurrentYear": {
                                                "val": "0.000"
                                            },
                                            "BudgetYearOneBase": {
                                                "val": "0.000"
                                            },
                                            "BudgetYearOneOCO": {
                                                "val": "0.000"
                                            },
                                            "BudgetYearOne": {
                                                "val": "0.000"
                                            },
                                            "BudgetYearTwo": {
                                                "val": "12.22"
                                            },
                                            "BudgetYearThree": {
                                                "val": "45.82"
                                            },
                                            "BudgetYearFour": {
                                                "val": "48.88"
                                            },
                                            "BudgetYearFive": {
                                                "val": "49.76"
                                            },
                                            "Total": {
                                                "val": "156.68"
                                            }
                                        }
                                    },
                                    {
                                        "Name": {
                                            "val": "National Airspace System (NAS) Plan"
                                        },
                                        "LineItemNumber": {
                                            "val": "833020"
                                        },
                                        "Cost": {
                                            "PriorYear": {
                                                "val": "0.841"
                                            },
                                            "CurrentYear": {
                                                "val": "0.000"
                                            },
                                            "BudgetYearOneBase": {
                                                "val": "0.000"
                                            },
                                            "BudgetYearOneOCO": {
                                                "val": "0.000"
                                            },
                                            "BudgetYearOne": {
                                                "val": "0.000"
                                            },
                                            "BudgetYearTwo": {
                                                "val": "0.000"
                                            },
                                            "BudgetYearThree": {
                                                "val": "0.000"
                                            },
                                            "BudgetYearFour": {
                                                "val": "0.000"
                                            },
                                            "BudgetYearFive": {
                                                "val": "0.000"
                                            },
                                            "Total": {
                                                "val": "0.841"
                                            }
                                        },
                                        "MDAPCode": {
                                            "val": "537"
                                        }
                                    },
                                    {
                                        "Name": {
                                            "val": "NAVSTAR Global Positioning System (Space and Control Segments)"
                                        },
                                        "LineItemNumber": {
                                            "val": "836730"
                                        },
                                        "Cost": {
                                            "PriorYear": {
                                                "val": "0.377"
                                            },
                                            "CurrentYear": {
                                                "val": "0.388"
                                            },
                                            "BudgetYearOneBase": {
                                                "val": "0.3"
                                            },
                                            "BudgetYearOneOCO": {
                                                "val": "0.000"
                                            },
                                            "BudgetYearOne": {
                                                "val": "0.3"
                                            },
                                            "BudgetYearTwo": {
                                                "val": "0.46"
                                            },
                                            "BudgetYearThree": {
                                                "val": "0.45"
                                            },
                                            "BudgetYearFour": {
                                                "val": "0.417"
                                            },
                                            "BudgetYearFive": {
                                                "val": "0.425"
                                            },
                                            "Total": {
                                                "val": "2.817"
                                            }
                                        },
                                        "MDAPCode": {
                                            "val": "166"
                                        }
                                    },
                                    {
                                        "Name": {
                                            "val": "NCMC - TW\/AA System"
                                        },
                                        "LineItemNumber": {
                                            "val": "838010"
                                        },
                                        "Cost": {
                                            "PriorYear": {
                                                "val": "0.748"
                                            },
                                            "CurrentYear": {
                                                "val": "0.774"
                                            },
                                            "BudgetYearOneBase": {
                                                "val": "0.597"
                                            },
                                            "BudgetYearOneOCO": {
                                                "val": "0.000"
                                            },
                                            "BudgetYearOne": {
                                                "val": "0.597"
                                            },
                                            "BudgetYearTwo": {
                                                "val": "0.909"
                                            },
                                            "BudgetYearThree": {
                                                "val": "0.886"
                                            },
                                            "BudgetYearFour": {
                                                "val": "0.826"
                                            },
                                            "BudgetYearFive": {
                                                "val": "0.841"
                                            },
                                            "Total": {
                                                "val": "5.581"
                                            }
                                        }
                                    },
                                    {
                                        "Name": {
                                            "val": "Region\/Sector Operation Control Center Modernization Program"
                                        },
                                        "LineItemNumber": {
                                            "val": "833030"
                                        },
                                        "Cost": {
                                            "PriorYear": {
                                                "val": "1.963"
                                            },
                                            "CurrentYear": {
                                                "val": "0.000"
                                            },
                                            "BudgetYearOneBase": {
                                                "val": "0.000"
                                            },
                                            "BudgetYearOneOCO": {
                                                "val": "0.000"
                                            },
                                            "BudgetYearOne": {
                                                "val": "0.000"
                                            },
                                            "BudgetYearTwo": {
                                                "val": "0.000"
                                            },
                                            "BudgetYearThree": {
                                                "val": "0.000"
                                            },
                                            "BudgetYearFour": {
                                                "val": "0.000"
                                            },
                                            "BudgetYearFive": {
                                                "val": "0.000"
                                            },
                                            "Total": {
                                                "val": "1.963"
                                            }
                                        }
                                    },
                                    {
                                        "Name": {
                                            "val": "Spacelift Range System  (SPACE)"
                                        },
                                        "LineItemNumber": {
                                            "val": "836770"
                                        },
                                        "Cost": {
                                            "PriorYear": {
                                                "val": "2.976"
                                            },
                                            "CurrentYear": {
                                                "val": "3.076"
                                            },
                                            "BudgetYearOneBase": {
                                                "val": "3.12"
                                            },
                                            "BudgetYearOneOCO": {
                                                "val": "0.000"
                                            },
                                            "BudgetYearOne": {
                                                "val": "3.12"
                                            },
                                            "BudgetYearTwo": {
                                                "val": "3.172"
                                            },
                                            "BudgetYearThree": {
                                                "val": "0.000"
                                            },
                                            "BudgetYearFour": {
                                                "val": "0.000"
                                            },
                                            "BudgetYearFive": {
                                                "val": "0.000"
                                            },
                                            "Total": {
                                                "val": "12.344"
                                            }
                                        }
                                    },
                                    {
                                        "Name": {
                                            "val": "WEATHER OBSERVATION\/FORECAST, PE 0305111F"
                                        },
                                        "LineItemNumber": {
                                            "val": "833070"
                                        },
                                        "Cost": {
                                            "PriorYear": {
                                                "val": "1.642"
                                            },
                                            "CurrentYear": {
                                                "val": "1.77"
                                            },
                                            "BudgetYearOneBase": {
                                                "val": "1.366"
                                            },
                                            "BudgetYearOneOCO": {
                                                "val": "0.000"
                                            },
                                            "BudgetYearOne": {
                                                "val": "1.366"
                                            },
                                            "BudgetYearTwo": {
                                                "val": "2.082"
                                            },
                                            "BudgetYearThree": {
                                                "val": "2.029"
                                            },
                                            "BudgetYearFour": {
                                                "val": "1.891"
                                            },
                                            "BudgetYearFive": {
                                                "val": "1.925"
                                            },
                                            "Total": {
                                                "val": "12.705"
                                            }
                                        }
                                    }
                                ]
                            }
                        }
                    ],
                    "SubtotalSparesCost": {
                        "PriorYear": {
                            "val": "22.115"
                        },
                        "CurrentYear": {
                            "val": "16.963"
                        },
                        "BudgetYearOneBase": {
                            "val": "25.746"
                        },
                        "BudgetYearOneOCO": {
                            "val": "0.000"
                        },
                        "BudgetYearOne": {
                            "val": "25.746"
                        },
                        "BudgetYearTwo": {
                            "val": "37.195"
                        },
                        "BudgetYearThree": {
                            "val": "62.194"
                        },
                        "BudgetYearFour": {
                            "val": "63.88"
                        },
                        "BudgetYearFive": {
                            "val": "63.826"
                        },
                        "Total": {
                            "val": "291.919"
                        }
                    }
                },
                "TotalSparesCost": {
                    "PriorYear": {
                        "val": "22.115"
                    },
                    "CurrentYear": {
                        "val": "16.963"
                    },
                    "BudgetYearOneBase": {
                        "val": "25.746"
                    },
                    "BudgetYearOneOCO": {
                        "val": "0.000"
                    },
                    "BudgetYearOne": {
                        "val": "25.746"
                    },
                    "BudgetYearTwo": {
                        "val": "37.195"
                    },
                    "BudgetYearThree": {
                        "val": "62.194"
                    },
                    "BudgetYearFour": {
                        "val": "63.88"
                    },
                    "BudgetYearFive": {
                        "val": "63.826"
                    },
                    "Total": {
                        "val": "291.919"
                    }
                }
            }
        },
        "DocumentAssemblyOptions": []
    }
}