{
    "id": "91029f30305011fa6b600cd14114fe96a15c0b72",
    "meta": {
        "filename": "dod-2017_PROCUREMENT_2017_NAVY_MARINECORPS_U_PROCUREMENT_JustificationBook_Navy_PB_2017.zzz_unzipped_U_PROCUREMENT_JustificationBook_Navy_PB_2017.xml",
        "budget_year": "2017",
        "budget_cycle": "PB",
        "submission_date": "2016-02",
        "service_agency_name": "Navy",
        "appropriation_code": "1109N",
        "appropriation_name": "Procurement, Marine Corps"
    },
    "record": {
        "@quantityUnits": "Each",
        "@unitCostUnits": "Dollars",
        "@totalCostUnits": "Millions",
        "@manufacturerRateUnits": "Yearly",
        "@classification": "UNCLASSIFIED",
        "LineItemNumber": {
            "val": "5050"
        },
        "LineItemTitle": {
            "val": "Motor Transport Modifications"
        },
        "P1LineNumber": {
            "val": "43"
        },
        "BudgetYear": {
            "val": "2017"
        },
        "BudgetCycle": {
            "val": "PB"
        },
        "SubmissionDate": {
            "val": "2016-02"
        },
        "ServiceAgencyName": {
            "val": "Navy"
        },
        "AppropriationNumber": {
            "val": "1109N"
        },
        "AppropriationTitle": {
            "val": "Procurement, Marine Corps"
        },
        "BudgetActivityNumber": {
            "val": "5"
        },
        "BudgetActivityTitle": {
            "val": "Support Vehicles"
        },
        "BudgetSubActivityNumber": {
            "val": "2"
        },
        "BudgetSubActivityTitle": {
            "val": "Tactical Vehicles"
        },
        "ResourceSummary": {
            "TotalCost": {
                "AllPriorYears": {
                    "val": "119.61"
                },
                "PriorYear": {
                    "val": "0.928"
                },
                "CurrentYear": {
                    "val": "7.743"
                },
                "BudgetYearOneBase": {
                    "val": "13.292"
                },
                "BudgetYearOneOCO": {
                    "val": "0"
                },
                "BudgetYearOne": {
                    "val": "13.292"
                },
                "BudgetYearTwo": {
                    "val": "11.887"
                },
                "BudgetYearThree": {
                    "val": "13.492"
                },
                "BudgetYearFour": {
                    "val": "13.782"
                },
                "BudgetYearFive": {
                    "val": "14.05"
                },
                "Continuing": {
                    "val": "true"
                }
            },
            "NetProcurementP1": {
                "AllPriorYears": {
                    "val": "119.61"
                },
                "PriorYear": {
                    "val": "0.928"
                },
                "CurrentYear": {
                    "val": "7.743"
                },
                "BudgetYearOneBase": {
                    "val": "13.292"
                },
                "BudgetYearOneOCO": {
                    "val": "0"
                },
                "BudgetYearOne": {
                    "val": "13.292"
                },
                "BudgetYearTwo": {
                    "val": "11.887"
                },
                "BudgetYearThree": {
                    "val": "13.492"
                },
                "BudgetYearFour": {
                    "val": "13.782"
                },
                "BudgetYearFive": {
                    "val": "14.05"
                },
                "Continuing": {
                    "val": "true"
                }
            },
            "TotalObligationAuthority": {
                "AllPriorYears": {
                    "val": "119.61"
                },
                "PriorYear": {
                    "val": "0.928"
                },
                "CurrentYear": {
                    "val": "7.743"
                },
                "BudgetYearOneBase": {
                    "val": "13.292"
                },
                "BudgetYearOneOCO": {
                    "val": "0"
                },
                "BudgetYearOne": {
                    "val": "13.292"
                },
                "BudgetYearTwo": {
                    "val": "11.887"
                },
                "BudgetYearThree": {
                    "val": "13.492"
                },
                "BudgetYearFour": {
                    "val": "13.782"
                },
                "BudgetYearFive": {
                    "val": "14.05"
                },
                "Continuing": {
                    "val": "true"
                }
            }
        },
        "Code": {
            "val": "B"
        },
        "OtherRelatedProgramElementList": {
            "ProgramElementNumber": [
                {
                    "val": "0206624M"
                }
            ]
        },
        "SecondaryDistribution": {
            "ComponentList": {
                "Component": [
                    {
                        "Name": {
                            "val": "Navy Active"
                        },
                        "Cost": {
                            "TotalCost": {
                                "PriorYear": {
                                    "val": "0.464"
                                },
                                "CurrentYear": {
                                    "val": "6.803"
                                },
                                "BudgetYearOneBase": {
                                    "val": "12.551"
                                },
                                "BudgetYearOne": {
                                    "val": "12.551"
                                },
                                "BudgetYearTwo": {
                                    "val": "11.695"
                                },
                                "BudgetYearThree": {
                                    "val": "13.27"
                                },
                                "BudgetYearFour": {
                                    "val": "13.547"
                                },
                                "BudgetYearFive": {
                                    "val": "13.81"
                                }
                            }
                        }
                    },
                    {
                        "Name": {
                            "val": "Navy Reserve"
                        },
                        "Cost": {
                            "TotalCost": {
                                "PriorYear": {
                                    "val": "0.464"
                                },
                                "CurrentYear": {
                                    "val": "0.94"
                                },
                                "BudgetYearOneBase": {
                                    "val": "0.741"
                                },
                                "BudgetYearOne": {
                                    "val": "0.741"
                                },
                                "BudgetYearTwo": {
                                    "val": "0.192"
                                },
                                "BudgetYearThree": {
                                    "val": "0.222"
                                },
                                "BudgetYearFour": {
                                    "val": "0.235"
                                },
                                "BudgetYearFive": {
                                    "val": "0.24"
                                }
                            }
                        }
                    }
                ]
            },
            "TotalCost": {
                "TotalCost": {
                    "PriorYear": {
                        "val": "0.928"
                    },
                    "CurrentYear": {
                        "val": "7.743"
                    },
                    "BudgetYearOneBase": {
                        "val": "13.292"
                    },
                    "BudgetYearOne": {
                        "val": "13.292"
                    },
                    "BudgetYearTwo": {
                        "val": "11.887"
                    },
                    "BudgetYearThree": {
                        "val": "13.492"
                    },
                    "BudgetYearFour": {
                        "val": "13.782"
                    },
                    "BudgetYearFive": {
                        "val": "14.05"
                    }
                }
            }
        },
        "Description": {
            "val": "The modifications program funds numerous essential modifications, initiatives, and new vehicle procurements that are required to address operational priorities, engineering change proposals, safety concerns, support equipment inefficiencies, tool malfunctions, product quality deficiencies, and other issues that affect vehicle reliability, availability and readiness. A proactive and focused approach ensures proper vehicle sustainment and life-cycle management and allows the program office to develop and implement improvements as needed to respond to the evolving requirements of the Marine Corps. Funding also addresses Medium Tactical Vehicle Replacement (MTVR) Energy Improvements to identify cost drivers in an effort to reduce fuel consumption over the life of the vehicle.\n\nFunding increases after FY 2016  reflect the inclusion of funding for Motor Transport Modifications previously funded in BLI 5230."
        },
        "Justification": {
            "val": "FY 2015 Base Appropriation:  \nFunds in the amount of $0.928M (Active: $0.464M, Reserves: $0.464M) provided for installations and other support such as integration brackets and cables for Logistics Vehicle System Replacement (LVSR) and Medium Tactical Vehicle Replacement (MTVR). \n\nMedium Tactical Vehicle Replacement (MTVR) Modification: $0.464M; Funding continued the installation of integration brackets and cables on the MTVR fleet of vehicles. Funding also continued to fund First Destination Transportation charges. \n\nLogistics Vehicle System Replacement (LVSR) Modification: $0.464M; Funding supported the installation of integration brackets and cables on the unarmored LVSR fleet of vehicles.\n\nFY 2016 Base Appropriation:  \nFunds in the amount of $7.743M (Active: $6.803M, Reserve: $0.940M) provides for installations and other support such as integration brackets and cables for Logistics Vehicle System Replacement (LVSR), installations of integration brackets and cables for the Medium Tactical Vehicle Replacement (MTVR).\n\nMedium Tactical Vehicle Replacement (MTVR) Modification: $5.433M; Funding continues the increased installation of integration brackets and cables on the MTVR fleet of vehicles. Funding also supports the vehicle ECP modifications and safety upgrades, which addresses issues that affect user requirements and life cycle issues, such as obsolescence, safety, and life cycle cost reductions. Funding also supports the production and installation of Fuel Efficiency upgrades in support of the Office of Naval Research (ONR) Future Naval Capability (FNC) Initiative. MTVR consumes a significant percentage of the USMC wheeled fleet energy consumption.  USMC requirement to reduce MTVR fuel consumption by 15%.  Funds allow for transition of 3 prototypes from ONR S&T to testing and procurement\/ installation on a fleet of 8,750 MTVRs.\n \nLogistics Vehicle System Replacement (LVSR) Modification: $2.310M; Funding continues to support the installation of integration brackets and cables on the LVSR fleet of vehicles as well as support for the vehicle Engineering Change Proposal (ECP) modifications and safety upgrades, which addresses issues that affect user requirements and life cycle issues, such as obsolescence, safety, and life cycle cost reductions. \n\nFY 2017 Base Appropriation Request:  \nFunds in the amount of $13.292M (Active: $12.551M, Reserve: $0.741M) will provide for installations and other support such as integration brackets and cables for Logistics Vehicle System Replacement (LVSR) and Medium Tactical Vehicle Replacement (MTVR). Will support the procurement of subsystems and components transitioned from the Office of Naval Research (ONR) Futures Naval Capability initiative for a fuel efficient MTVR and funds procurement and modifications to ground transportation systems and provides for the procurement, sustainment, and life-cycle management of vehicles to implement improvements in response to known and emergent needs of the Marine Corps Motor Transport Modifications (MTM). The increase of $5.549M from FY16 to FY17 is due to the realignment of Motor Transport Modification efforts from BLI 5230.\n\nMedium Tactical Vehicle Replacement (MTVR) Modification: $7.222M; Funding will continue the installation of integration brackets and cables on the MTVR fleet of vehicles. Will continue to support the procurement of subsystems and components transitioned from the Office of Naval Research (ONR) Future Naval Capability initiative for a fuel efficient MTVR. The increase of $1.789M from FY16 to FY17 will support the procurement phase of the Fuel Efficient MTVR initiative.\n\nLogistics Vehicle System Replacement (LVSR) Modification: $1.768M; Funding will continue to support the installation of integration brackets and cables on the LVSR fleet of vehicles as well as supporting the vehicle Engineering Change Proposal (ECP) modifications and safety upgrades, which addresses issues that affect user requirements and life cycle issues, such as obsolescence, safety, and life cycle cost reductions. The decrease of $0.542M from FY16 to FY17 supports reduced number of Engineering\/Safety modifications.\n\nMotor Transport Modifications (MTM): $4.302M; Funding will provide for the implementation of the fleet service life extension initiatives, vehicles, quality deficiency resolutions, safety initiatives, and environmental\/ state transportation mandated vehicle changes. Provides support for Engineering Change Proposal (ECP) integration, testing and fielding efforts for hosted systems i.e. C4I, weapons, and intel that use light tactical vehicles as their base transportation mode. Additional efforts include updates to ambulance conversion kits and technical data plates. Motor Transport Modifications is funded under BLI 5230 for FY16 and prior. The increase of $3.194M from FY16 to FY17 will support the fleet service life extension initiatives for all legacy vehicles and associated equipment."
        },
        "ItemExhibitList": {
            "P40AItemGroup": [
                {
                    "Name": {
                        "val": "Motor Transport Modifications"
                    },
                    "CategoryList": {
                        "Category": [
                            {
                                "Name": {
                                    "val": "1) Medium Tactical Vehicle Replacement (MTVR) Modifications"
                                },
                                "ItemList": {
                                    "Item": [
                                        {
                                            "Name": {
                                                "val": "1.1) Vehicle Safety Modifications\/Upgrades Proc & Installs"
                                            },
                                            "ItemNumber": [],
                                            "IdCode": {
                                                "val": "A"
                                            },
                                            "ResourceSummary": {
                                                "TotalCost": {
                                                    "CurrentYear": {
                                                        "val": "1.911"
                                                    },
                                                    "BudgetYearOneBase": {
                                                        "val": "1.16"
                                                    },
                                                    "BudgetYearOne": {
                                                        "val": "1.16"
                                                    }
                                                }
                                            }
                                        },
                                        {
                                            "Name": {
                                                "val": "1.2) Vehicle ECP Integration Equipment & Installs"
                                            },
                                            "ItemNumber": [],
                                            "IdCode": {
                                                "val": "A"
                                            },
                                            "ResourceSummary": {
                                                "TotalCost": {
                                                    "AllPriorYears": {
                                                        "val": "40.611"
                                                    },
                                                    "PriorYear": {
                                                        "val": "0.262"
                                                    },
                                                    "CurrentYear": {
                                                        "val": "2.31"
                                                    },
                                                    "BudgetYearOneBase": {
                                                        "val": "2.25"
                                                    },
                                                    "BudgetYearOne": {
                                                        "val": "2.25"
                                                    }
                                                }
                                            }
                                        },
                                        {
                                            "Name": {
                                                "val": "1.3) Energy Efficiency Initiative"
                                            },
                                            "ItemNumber": [],
                                            "IdCode": {
                                                "val": "B"
                                            },
                                            "ResourceSummary": {
                                                "TotalCost": {
                                                    "CurrentYear": {
                                                        "val": "1.212"
                                                    },
                                                    "BudgetYearOneBase": {
                                                        "val": "3.362"
                                                    },
                                                    "BudgetYearOne": {
                                                        "val": "3.362"
                                                    }
                                                }
                                            }
                                        },
                                        {
                                            "Name": {
                                                "val": "1.4) Energy Initiative Program Support"
                                            },
                                            "ItemNumber": [],
                                            "IdCode": {
                                                "val": "A"
                                            },
                                            "ResourceSummary": {
                                                "TotalCost": {
                                                    "BudgetYearOneBase": {
                                                        "val": "0.45"
                                                    },
                                                    "BudgetYearOne": {
                                                        "val": "0.45"
                                                    }
                                                }
                                            }
                                        },
                                        {
                                            "Name": {
                                                "val": "1.5) First Destination Transportation"
                                            },
                                            "ItemNumber": [],
                                            "IdCode": {
                                                "val": "A"
                                            },
                                            "ResourceSummary": {
                                                "TotalCost": {
                                                    "AllPriorYears": {
                                                        "val": "1.354"
                                                    },
                                                    "PriorYear": {
                                                        "val": "0.202"
                                                    }
                                                }
                                            }
                                        },
                                        {
                                            "Name": {
                                                "val": "1.6) Prior Years Cumulative Funding"
                                            },
                                            "ItemNumber": [],
                                            "IdCode": {
                                                "val": "A"
                                            },
                                            "ResourceSummary": {
                                                "TotalCost": {
                                                    "AllPriorYears": {
                                                        "val": "7.789"
                                                    }
                                                }
                                            }
                                        }
                                    ]
                                },
                                "CategorySubtotal": {
                                    "TotalCost": {
                                        "AllPriorYears": {
                                            "val": "49.754"
                                        },
                                        "PriorYear": {
                                            "val": "0.464"
                                        },
                                        "CurrentYear": {
                                            "val": "5.433"
                                        },
                                        "BudgetYearOneBase": {
                                            "val": "7.222"
                                        },
                                        "BudgetYearOne": {
                                            "val": "7.222"
                                        }
                                    }
                                }
                            },
                            {
                                "Name": {
                                    "val": "2) LVSR Mods"
                                },
                                "ItemList": {
                                    "Item": [
                                        {
                                            "Name": {
                                                "val": "2.1) LVSR Systems Integrations Equip & Installs (GFE, TOCNET, etc)"
                                            },
                                            "ItemNumber": [],
                                            "IdCode": {
                                                "val": "A"
                                            },
                                            "ResourceSummary": {
                                                "TotalCost": {
                                                    "AllPriorYears": {
                                                        "val": "24.058"
                                                    },
                                                    "CurrentYear": {
                                                        "val": "0.2"
                                                    },
                                                    "BudgetYearOneBase": {
                                                        "val": "0.2"
                                                    },
                                                    "BudgetYearOne": {
                                                        "val": "0.2"
                                                    }
                                                }
                                            }
                                        },
                                        {
                                            "Name": {
                                                "val": "2.2) Vehicle Safety Mods\/Upgrades"
                                            },
                                            "ItemNumber": [],
                                            "IdCode": {
                                                "val": "A"
                                            },
                                            "ResourceSummary": {
                                                "TotalCost": {
                                                    "AllPriorYears": {
                                                        "val": "12.062"
                                                    },
                                                    "CurrentYear": {
                                                        "val": "0.585"
                                                    },
                                                    "BudgetYearOneBase": {
                                                        "val": "0.403"
                                                    },
                                                    "BudgetYearOne": {
                                                        "val": "0.403"
                                                    }
                                                }
                                            }
                                        },
                                        {
                                            "Name": {
                                                "val": "2.3) LVSR Modification Kits (ECPs)"
                                            },
                                            "ItemNumber": [],
                                            "IdCode": {
                                                "val": "A"
                                            },
                                            "ResourceSummary": {
                                                "TotalCost": {
                                                    "AllPriorYears": {
                                                        "val": "19.625"
                                                    },
                                                    "CurrentYear": {
                                                        "val": "0.585"
                                                    },
                                                    "BudgetYearOneBase": {
                                                        "val": "0.417"
                                                    },
                                                    "BudgetYearOne": {
                                                        "val": "0.417"
                                                    }
                                                }
                                            }
                                        },
                                        {
                                            "Name": {
                                                "val": "2.4) USMC Bridge Pallets Adapters"
                                            },
                                            "ItemNumber": [],
                                            "IdCode": {
                                                "val": "A"
                                            },
                                            "ResourceSummary": {
                                                "Quantity": {
                                                    "AllPriorYears": {
                                                        "val": "35"
                                                    }
                                                },
                                                "TotalCost": {
                                                    "AllPriorYears": {
                                                        "val": "1.3"
                                                    }
                                                },
                                                "UnitCost": {
                                                    "AllPriorYears": {
                                                        "val": "37142.86"
                                                    }
                                                }
                                            }
                                        },
                                        {
                                            "Name": {
                                                "val": "2.5) Emergency Egress Hatch"
                                            },
                                            "ItemNumber": [],
                                            "IdCode": {
                                                "val": "A"
                                            },
                                            "ResourceSummary": {
                                                "Quantity": {
                                                    "AllPriorYears": {
                                                        "val": "600"
                                                    }
                                                },
                                                "TotalCost": {
                                                    "AllPriorYears": {
                                                        "val": "0.3"
                                                    }
                                                },
                                                "UnitCost": {
                                                    "AllPriorYears": {
                                                        "val": "500"
                                                    }
                                                }
                                            }
                                        },
                                        {
                                            "Name": {
                                                "val": "2.6) AFES Installs"
                                            },
                                            "ItemNumber": [],
                                            "IdCode": {
                                                "val": "A"
                                            },
                                            "ResourceSummary": {
                                                "TotalCost": {
                                                    "AllPriorYears": {
                                                        "val": "1"
                                                    }
                                                }
                                            }
                                        },
                                        {
                                            "Name": {
                                                "val": "2.7) Macaw Back packs and Halligan Tool Bracket Sets"
                                            },
                                            "ItemNumber": [],
                                            "IdCode": {
                                                "val": "A"
                                            },
                                            "ResourceSummary": {
                                                "TotalCost": {
                                                    "AllPriorYears": {
                                                        "val": "0.2"
                                                    }
                                                }
                                            }
                                        },
                                        {
                                            "Name": {
                                                "val": "2.8) LVSR Reserves (ECP, Safety & Integration)"
                                            },
                                            "ItemNumber": [],
                                            "ResourceSummary": {
                                                "TotalCost": {
                                                    "AllPriorYears": {
                                                        "val": "1.579"
                                                    },
                                                    "PriorYear": {
                                                        "val": "0.464"
                                                    },
                                                    "CurrentYear": {
                                                        "val": "0.94"
                                                    },
                                                    "BudgetYearOneBase": {
                                                        "val": "0.748"
                                                    },
                                                    "BudgetYearOne": {
                                                        "val": "0.748"
                                                    }
                                                }
                                            }
                                        },
                                        {
                                            "Name": {
                                                "val": "2.9) Logistics Support (ILS, Factory Trng, etc)"
                                            },
                                            "ItemNumber": [],
                                            "ResourceSummary": {
                                                "TotalCost": {
                                                    "AllPriorYears": {
                                                        "val": "5.735"
                                                    }
                                                }
                                            }
                                        },
                                        {
                                            "Name": {
                                                "val": "2.10) Program Office Support"
                                            },
                                            "ItemNumber": [],
                                            "ResourceSummary": {
                                                "TotalCost": {
                                                    "AllPriorYears": {
                                                        "val": "3.997"
                                                    }
                                                }
                                            }
                                        }
                                    ]
                                },
                                "CategorySubtotal": {
                                    "TotalCost": {
                                        "AllPriorYears": {
                                            "val": "69.856"
                                        },
                                        "PriorYear": {
                                            "val": "0.464"
                                        },
                                        "CurrentYear": {
                                            "val": "2.31"
                                        },
                                        "BudgetYearOneBase": {
                                            "val": "1.768"
                                        },
                                        "BudgetYearOne": {
                                            "val": "1.768"
                                        }
                                    }
                                }
                            },
                            {
                                "Name": {
                                    "val": "3) Motor Transport Mods"
                                },
                                "ItemList": {
                                    "Item": [
                                        {
                                            "Name": {
                                                "val": "3.1) M1035A2\/D1002 Ambulance Conversion"
                                            },
                                            "ItemNumber": [],
                                            "IdCode": {
                                                "val": "A"
                                            },
                                            "ResourceSummary": {
                                                "TotalCost": {
                                                    "BudgetYearOneBase": {
                                                        "val": "2"
                                                    },
                                                    "BudgetYearOne": {
                                                        "val": "2"
                                                    }
                                                }
                                            }
                                        },
                                        {
                                            "Name": {
                                                "val": "3.2) Safety Modifications"
                                            },
                                            "ItemNumber": [],
                                            "IdCode": {
                                                "val": "B"
                                            },
                                            "ResourceSummary": {
                                                "TotalCost": {
                                                    "BudgetYearOneBase": {
                                                        "val": "0.175"
                                                    },
                                                    "BudgetYearOne": {
                                                        "val": "0.175"
                                                    }
                                                }
                                            }
                                        },
                                        {
                                            "Name": {
                                                "val": "3.3) Reliability Engineering"
                                            },
                                            "ItemNumber": [],
                                            "IdCode": {
                                                "val": "A"
                                            },
                                            "ResourceSummary": {
                                                "TotalCost": {
                                                    "BudgetYearOneBase": {
                                                        "val": "1"
                                                    },
                                                    "BudgetYearOne": {
                                                        "val": "1"
                                                    }
                                                }
                                            }
                                        },
                                        {
                                            "Name": {
                                                "val": "3.4) Program Integration"
                                            },
                                            "ItemNumber": [],
                                            "IdCode": {
                                                "val": "B"
                                            },
                                            "ResourceSummary": {
                                                "TotalCost": {
                                                    "BudgetYearOneBase": {
                                                        "val": "1.082"
                                                    },
                                                    "BudgetYearOne": {
                                                        "val": "1.082"
                                                    }
                                                }
                                            }
                                        },
                                        {
                                            "Name": {
                                                "val": "3.5) Technical Publications"
                                            },
                                            "ItemNumber": [],
                                            "IdCode": {
                                                "val": "A"
                                            },
                                            "ResourceSummary": {
                                                "TotalCost": {
                                                    "BudgetYearOneBase": {
                                                        "val": "0.045"
                                                    },
                                                    "BudgetYearOne": {
                                                        "val": "0.045"
                                                    }
                                                }
                                            }
                                        }
                                    ]
                                },
                                "CategorySubtotal": {
                                    "TotalCost": {
                                        "AllPriorYears": {
                                            "val": "0"
                                        },
                                        "BudgetYearOneBase": {
                                            "val": "4.302"
                                        },
                                        "BudgetYearOne": {
                                            "val": "4.302"
                                        }
                                    }
                                }
                            }
                        ]
                    },
                    "TotalCost": {
                        "TotalCost": {
                            "AllPriorYears": {
                                "val": "119.61"
                            },
                            "PriorYear": {
                                "val": "0.928"
                            },
                            "CurrentYear": {
                                "val": "7.743"
                            },
                            "BudgetYearOneBase": {
                                "val": "13.292"
                            },
                            "BudgetYearOne": {
                                "val": "13.292"
                            }
                        }
                    }
                }
            ]
        },
        "DocumentAssemblyOptions": {
            "p40AItemScheduleSetting": {
                "val": "total"
            }
        }
    }
}